{"cameraMode":{"drawMode":0,"name":"Shaded","section":"Shading Mode"},"sceneLighting":true,"audioPlay":false,"sceneViewState":{"m_AlwaysRefresh":false,"showFog":true,"showSkybox":true,"showFlares":true,"showImageEffects":true,"showParticleSystems":true,"showVisualEffectGraphs":true,"m_FxEnabled":true},"in2DMode":false,"pivot":{"x":5.669158935546875,"y":0.01671600341796875,"z":65.78228759765625},"rotation":{"x":-0.1233789324760437,"y":0.6235396265983582,"z":-0.09978628903627396,"w":-0.7658768892288208},"size":57.375728607177737,"orthographic":false}